main.py
ppecli-0.1.0.dist-info/licenses/LICENSE
ppecli-0.1.0.dist-info/METADATA
ppecli-0.1.0.dist-info/WHEEL
ppecli-0.1.0.dist-info/entry_points.txt
ppecli-0.1.0.dist-info/top_level.txt
ppecli-0.1.0.dist-info/RECORD
