Metadata-Version: 2.4
Name: ppecli
Version: 0.1.0
Summary: Python Ping with Emoji
Author-email: Froas <froas.dev@gmail.com>
License-File: LICENSE
Requires-Dist: requests
Dynamic: license-file
